ldapauthenticator/__init__.py
ldapauthenticator/ldapauthenticator.py
yqn_jupyterhub_ldapauthenticator-1.6.1.dev0.dist-info/LICENSE
yqn_jupyterhub_ldapauthenticator-1.6.1.dev0.dist-info/METADATA
yqn_jupyterhub_ldapauthenticator-1.6.1.dev0.dist-info/WHEEL
yqn_jupyterhub_ldapauthenticator-1.6.1.dev0.dist-info/top_level.txt
yqn_jupyterhub_ldapauthenticator-1.6.1.dev0.dist-info/RECORD
