Metadata-Version: 2.1
Name: yqn-jupyterhub-ldapauthenticator
Version: 1.6.1.dev0
Summary: LDAP Authenticator for JupyterHub
Home-page: https://github.com/jupyterhub/ldapauthenticator
Author: Yuvi Panda
Author-email: yuvipanda@riseup.net
License: 3 Clause BSD
Platform: UNKNOWN
Requires-Dist: jupyterhub
Requires-Dist: ldap3
Requires-Dist: tornado
Requires-Dist: traitlets
